Workbook

Sheet README
A1: NAV facility stress model (formula version)
A2: Hypothetical inputs for illustration. Not observed market terms, not advice, and not any rating agency's methodology.
A4: What it does
A5: Computes eligible NAV after a single-asset cap and a top-N concentration limit, LTV, the status against the cash-sweep
A6: and breach levels, a diversity covenant, the uniform drawdown to each level, the cure to target, and the effect of
A7: writing off the largest assets. It reproduces the Python model in src/fundfinancelab/nav_facility.py.
A9: How to use
A10: Edit only the blue cells on Inputs (facility terms and up to 20 assets). Yellow marks the key assumptions.
A11: Leave Top-N count and share blank to switch that limit off; leave Minimum assets blank to switch the covenant off.
A12: Every other cell is a formula. Checks shows whether the workbook is internally consistent.
A14: Sheets
A15: Inputs - facility terms and portfolio. Calc - eligible NAV, LTV, status, headroom. Uniform stress - drawdown grid.
... A22: Status: breach if LTV >= breach level; cash sweep if LTV >= sweep level or the diversity covenant fails; else ok.

Sheet Inputs
A1: Inputs (edit blue cells only)
B3: Facility terms
B5: Loan outstanding (USD m) | C5: 150 | D5: Hypothetical | F5: Legend
B6: Cash-sweep LTV | C6: 0.2 | D6: Sweep applies at or above this LTV | F6: Blue text = input
B7: Breach LTV | C7: 0.25 | D7: Covenant breach at or above this LTV | F7: Yellow fill = key assumption
B8: Cure target LTV | C8: 0.15 | D8: LTV the borrower must restore after a breach | F8: Source: examples/nav_facility_covenants_hypothetical.json (hypothetical)
B9: Single-asset cap (share of total NAV) | C9: 0.2 | D9: Each asset counts up to this share
B10: Top-N count | C10: 5 | D10: Blank = no top-N limit
B11: Top-N share of eligible NAV | C11: 0.6 | D11: Blank = no top-N limit
B12: Minimum assets (diversity covenant) | C12: 10 | D12: Blank = no covenant
B13: Single-name loss (share written off) | C13: 1 | D13: Used on Single-name
B15: Portfolio (up to 20 assets; USD m; hypothetical)
B16: Asset | C16: NAV (USD m)
B17: Asset A | C17: 240
B18: Asset B | C18: 150
B19: Asset C | C19: 120
B20: Asset D | C20: 100
B21: Asset E | C21: 90
B22: Asset F | C22: 80
B23: Asset G | C23: 70
B24: Asset H | C24: 60
B25: Asset I | C25: 40
B26: Asset J | C26: 30
B27: Asset K | C27: 20

Sheet Calc
A1: Eligible NAV, LTV and status
B16: Asset | C16: NAV | D16: NAV rank | E16: Capped NAV | F16: Capped rank | G16: In top N
B17: =IF(Inputs!B17="","",Inputs!B17) -> Asset A | C17: =IF(ISNUMBER(Inputs!C17),Inputs!C17,0) -> 240 | D17: =IF(C17>0,RANK(C17,$C$17:$C$36,0)+COUNTIF(C$16:C16,C17),999) -> 1 | E17: =MIN(C17,Inputs!$C$9*$C$38) -> 200 | F17: =RANK(E17,$E$17:$E$36,0)+COUNTIF(E$16:E16,E17) -> 1 | G17: =IF(AND(ISNUMBER(Inputs!$C$10),F17<=Inputs!$C$10),1,0) -> 1
B18: =IF(Inputs!B18="","",Inputs!B18) -> Asset B | C18: =IF(ISNUMBER(Inputs!C18),Inputs!C18,0) -> 150 | D18: =IF(C18>0,RANK(C18,$C$17:$C$36,0)+COUNTIF(C$16:C17,C18),999) -> 2 | E18: =MIN(C18,Inputs!$C$9*$C$38) -> 150 | F18: =RANK(E18,$E$17:$E$36,0)+COUNTIF(E$16:E17,E18) -> 2 | G18: =IF(AND(ISNUMBER(Inputs!$C$10),F18<=Inputs!$C$10),1,0) -> 1
B19: =IF(Inputs!B19="","",Inputs!B19) -> Asset C | C19: =IF(ISNUMBER(Inputs!C19),Inputs!C19,0) -> 120 | D19: =IF(C19>0,RANK(C19,$C$17:$C$36,0)+COUNTIF(C$16:C18,C19),999) -> 3 | E19: =MIN(C19,Inputs!$C$9*$C$38) -> 120 | F19: =RANK(E19,$E$17:$E$36,0)+COUNTIF(E$16:E18,E19) -> 3 | G19: =IF(AND(ISNUMBER(Inputs!$C$10),F19<=Inputs!$C$10),1,0) -> 1
B20: =IF(Inputs!B20="","",Inputs!B20) -> Asset D | C20: =IF(ISNUMBER(Inputs!C20),Inputs!C20,0) -> 100 | D20: =IF(C20>0,RANK(C20,$C$17:$C$36,0)+COUNTIF(C$16:C19,C20),999) -> 4 | E20: =MIN(C20,Inputs!$C$9*$C$38) -> 100 | F20: =RANK(E20,$E$17:$E$36,0)+COUNTIF(E$16:E19,E20) -> 4 | G20: =IF(AND(ISNUMBER(Inputs!$C$10),F20<=Inputs!$C$10),1,0) -> 1
B21: =IF(Inputs!B21="","",Inputs!B21) -> Asset E | C21: =IF(ISNUMBER(Inputs!C21),Inputs!C21,0) -> 90 | D21: =IF(C21>0,RANK(C21,$C$17:$C$36,0)+COUNTIF(C$16:C20,C21),999) -> 5 | E21: =MIN(C21,Inputs!$C$9*$C$38) -> 90 | F21: =RANK(E21,$E$17:$E$36,0)+COUNTIF(E$16:E20,E21) -> 5 | G21: =IF(AND(ISNUMBER(Inputs!$C$10),F21<=Inputs!$C$10),1,0) -> 1
B22: =IF(Inputs!B22="","",Inputs!B22) -> Asset F | C22: =IF(ISNUMBER(Inputs!C22),Inputs!C22,0) -> 80 | D22: =IF(C22>0,RANK(C22,$C$17:$C$36,0)+COUNTIF(C$16:C21,C22),999) -> 6 | E22: =MIN(C22,Inputs!$C$9*$C$38) -> 80 | F22: =RANK(E22,$E$17:$E$36,0)+COUNTIF(E$16:E21,E22) -> 6 | G22: =IF(AND(ISNUMBER(Inputs!$C$10),F22<=Inputs!$C$10),1,0) -> 0
B23: =IF(Inputs!B23="","",Inputs!B23) -> Asset G | C23: =IF(ISNUMBER(Inputs!C23),Inputs!C23,0) -> 70 | D23: =IF(C23>0,RANK(C23,$C$17:$C$36,0)+COUNTIF(C$16:C22,C23),999) -> 7 | E23: =MIN(C23,Inputs!$C$9*$C$38) -> 70 | F23: =RANK(E23,$E$17:$E$36,0)+COUNTIF(E$16:E22,E23) -> 7 | G23: =IF(AND(ISNUMBER(Inputs!$C$10),F23<=Inputs!$C$10),1,0) -> 0
B24: =IF(Inputs!B24="","",Inputs!B24) -> Asset H | C24: =IF(ISNUMBER(Inputs!C24),Inputs!C24,0) -> 60 | D24: =IF(C24>0,RANK(C24,$C$17:$C$36,0)+COUNTIF(C$16:C23,C24),999) -> 8 | E24: =MIN(C24,Inputs!$C$9*$C$38) -> 60 | F24: =RANK(E24,$E$17:$E$36,0)+COUNTIF(E$16:E23,E24) -> 8 | G24: =IF(AND(ISNUMBER(Inputs!$C$10),F24<=Inputs!$C$10),1,0) -> 0
B25: =IF(Inputs!B25="","",Inputs!B25) -> Asset I | C25: =IF(ISNUMBER(Inputs!C25),Inputs!C25,0) -> 40 | D25: =IF(C25>0,RANK(C25,$C$17:$C$36,0)+COUNTIF(C$16:C24,C25),999) -> 9 | E25: =MIN(C25,Inputs!$C$9*$C$38) -> 40 | F25: =RANK(E25,$E$17:$E$36,0)+COUNTIF(E$16:E24,E25) -> 9 | G25: =IF(AND(ISNUMBER(Inputs!$C$10),F25<=Inputs!$C$10),1,0) -> 0
B26: =IF(Inputs!B26="","",Inputs!B26) -> Asset J | C26: =IF(ISNUMBER(Inputs!C26),Inputs!C26,0) -> 30 | D26: =IF(C26>0,RANK(C26,$C$17:$C$36,0)+COUNTIF(C$16:C25,C26),999) -> 10 | E26: =MIN(C26,Inputs!$C$9*$C$38) -> 30 | F26: =RANK(E26,$E$17:$E$36,0)+COUNTIF(E$16:E25,E26) -> 10 | G26: =IF(AND(ISNUMBER(Inputs!$C$10),F26<=Inputs!$C$10),1,0) -> 0
B27: =IF(Inputs!B27="","",Inputs!B27) -> Asset K | C27: =IF(ISNUMBER(Inputs!C27),Inputs!C27,0) -> 20 | D27: =IF(C27>0,RANK(C27,$C$17:$C$36,0)+COUNTIF(C$16:C26,C27),999) -> 11 | E27: =MIN(C27,Inputs!$C$9*$C$38) -> 20 | F27: =RANK(E27,$E$17:$E$36,0)+COUNTIF(E$16:E26,E27) -> 11 | G27: =IF(AND(ISNUMBER(Inputs!$C$10),F27<=Inputs!$C$10),1,0) -> 0
B28: =IF(Inputs!B28="","",Inputs!B28) | C28: =IF(ISNUMBER(Inputs!C28),Inputs!C28,0) -> 0 | D28: =IF(C28>0,RANK(C28,$C$17:$C$36,0)+COUNTIF(C$16:C27,C28),999) -> 999 | E28: =MIN(C28,Inputs!$C$9*$C$38) -> 0 | F28: =RANK(E28,$E$17:$E$36,0)+COUNTIF(E$16:E27,E28) -> 12 | G28: =IF(AND(ISNUMBER(Inputs!$C$10),F28<=Inputs!$C$10),1,0) -> 0
... B36: =IF(Inputs!B36="","",Inputs!B36) | C36: =IF(ISNUMBER(Inputs!C36),Inputs!C36,0) -> 0 | D36: =IF(C36>0,RANK(C36,$C$17:$C$36,0)+COUNTIF(C$16:C35,C36),999) -> 999 | E36: =MIN(C36,Inputs!$C$9*$C$38) -> 0 | F36: =RANK(E36,$E$17:$E$36,0)+COUNTIF(E$16:E35,E36) -> 20 | G36: =IF(AND(ISNUMBER(Inputs!$C$10),F36<=Inputs!$C$10),1,0) -> 0
B38: Total NAV | C38: =SUM(C17:C36) -> 1000
B39: Eligible NAV after single-asset cap | C39: =SUM(E17:E36) -> 960
B40: Top-N capped total | C40: =SUMPRODUCT(E17:E36,G17:G36) -> 660
B41: Excluded by top-N limit | C41: =IF(AND(ISNUMBER(Inputs!C10),ISNUMBER(Inputs!C11)),MAX(0,C40-Inputs!C11*C39),0) -> 84
B42: Eligible NAV | C42: =C39-C41 -> 876
B43: Excluded by single-asset cap | C43: =C38-C39 -> 40
B44: LTV | C44: =IF(C42>0,Inputs!C5/C42,"n/a") -> 0.17123288
B45: Assets with value | C45: =COUNTIF(C17:C36,">0") -> 11
B46: Diversity covenant met | C46: =IF(ISNUMBER(Inputs!C12),C45>=Inputs!C12,TRUE()) -> TRUE
B47: Status | C47: =IF(C44>=Inputs!C7,"breach",IF(OR(C44>=Inputs!C6,NOT(C46)),"cash sweep","ok")) -> ok
B48: Uniform drawdown to cash-sweep level | C48: =MAX(0,1-Inputs!C5/(Inputs!C6*C42)) -> 0.14383562
B49: Uniform drawdown to breach level | C49: =MAX(0,1-Inputs!C5/(Inputs!C7*C42)) -> 0.31506849
B50: Cure to target (if in breach) | C50: =IF(C44>=Inputs!C7,Inputs!C5-Inputs!C8*C42,0) -> 0
B52: NAV rank 999 marks an empty row. Ranks break ties by row order, as the Python model does.

Sheet Uniform stress
A1: Uniform drawdowns
A3: Eligible NAV at drawdown d = eligible NAV x (1 - d): every NAV, cap and limit scales together.
A5: Drawdown | B5: Eligible NAV | C5: LTV | D5: Status | E5: Cure to target
A6: 0 | B6: =Calc!$C$42*(1-A6) -> 876 | C6: =IF(B6>0,Inputs!$C$5/B6,"n/a") -> 0.17123288 | D6: =IF(C6>=Inputs!$C$7,"breach",IF(OR(C6>=Inputs!$C$6,NOT(Calc!$C$46)),"cash sweep","ok")) -> ok | E6: =IF(C6>=Inputs!$C$7,Inputs!$C$5-Inputs!$C$8*B6,0) -> 0
A7: 0.05 | B7: =Calc!$C$42*(1-A7) -> 832.2 | C7: =IF(B7>0,Inputs!$C$5/B7,"n/a") -> 0.18024513 | D7: =IF(C7>=Inputs!$C$7,"breach",IF(OR(C7>=Inputs!$C$6,NOT(Calc!$C$46)),"cash sweep","ok")) -> ok | E7: =IF(C7>=Inputs!$C$7,Inputs!$C$5-Inputs!$C$8*B7,0) -> 0
A8: 0.1 | B8: =Calc!$C$42*(1-A8) -> 788.4 | C8: =IF(B8>0,Inputs!$C$5/B8,"n/a") -> 0.19025875 | D8: =IF(C8>=Inputs!$C$7,"breach",IF(OR(C8>=Inputs!$C$6,NOT(Calc!$C$46)),"cash sweep","ok")) -> ok | E8: =IF(C8>=Inputs!$C$7,Inputs!$C$5-Inputs!$C$8*B8,0) -> 0
A9: 0.15 | B9: =Calc!$C$42*(1-A9) -> 744.6 | C9: =IF(B9>0,Inputs!$C$5/B9,"n/a") -> 0.20145044 | D9: =IF(C9>=Inputs!$C$7,"breach",IF(OR(C9>=Inputs!$C$6,NOT(Calc!$C$46)),"cash sweep","ok")) -> cash sweep | E9: =IF(C9>=Inputs!$C$7,Inputs!$C$5-Inputs!$C$8*B9,0) -> 0
A10: 0.2 | B10: =Calc!$C$42*(1-A10) -> 700.8 | C10: =IF(B10>0,Inputs!$C$5/B10,"n/a") -> 0.2140411 | D10: =IF(C10>=Inputs!$C$7,"breach",IF(OR(C10>=Inputs!$C$6,NOT(Calc!$C$46)),"cash sweep","ok")) -> cash sweep | E10: =IF(C10>=Inputs!$C$7,Inputs!$C$5-Inputs!$C$8*B10,0) -> 0
A11: 0.25 | B11: =Calc!$C$42*(1-A11) -> 657 | C11: =IF(B11>0,Inputs!$C$5/B11,"n/a") -> 0.2283105 | D11: =IF(C11>=Inputs!$C$7,"breach",IF(OR(C11>=Inputs!$C$6,NOT(Calc!$C$46)),"cash sweep","ok")) -> cash sweep | E11: =IF(C11>=Inputs!$C$7,Inputs!$C$5-Inputs!$C$8*B11,0) -> 0
A12: 0.3 | B12: =Calc!$C$42*(1-A12) -> 613.2 | C12: =IF(B12>0,Inputs!$C$5/B12,"n/a") -> 0.2446184 | D12: =IF(C12>=Inputs!$C$7,"breach",IF(OR(C12>=Inputs!$C$6,NOT(Calc!$C$46)),"cash sweep","ok")) -> cash sweep | E12: =IF(C12>=Inputs!$C$7,Inputs!$C$5-Inputs!$C$8*B12,0) -> 0
A13: 0.35 | B13: =Calc!$C$42*(1-A13) -> 569.4 | C13: =IF(B13>0,Inputs!$C$5/B13,"n/a") -> 0.26343519 | D13: =IF(C13>=Inputs!$C$7,"breach",IF(OR(C13>=Inputs!$C$6,NOT(Calc!$C$46)),"cash sweep","ok")) -> breach | E13: =IF(C13>=Inputs!$C$7,Inputs!$C$5-Inputs!$C$8*B13,0) -> 64.59
A14: 0.4 | B14: =Calc!$C$42*(1-A14) -> 525.6 | C14: =IF(B14>0,Inputs!$C$5/B14,"n/a") -> 0.28538813 | D14: =IF(C14>=Inputs!$C$7,"breach",IF(OR(C14>=Inputs!$C$6,NOT(Calc!$C$46)),"cash sweep","ok")) -> breach | E14: =IF(C14>=Inputs!$C$7,Inputs!$C$5-Inputs!$C$8*B14,0) -> 71.16
A15: 0.45 | B15: =Calc!$C$42*(1-A15) -> 481.8 | C15: =IF(B15>0,Inputs!$C$5/B15,"n/a") -> 0.3113325 | D15: =IF(C15>=Inputs!$C$7,"breach",IF(OR(C15>=Inputs!$C$6,NOT(Calc!$C$46)),"cash sweep","ok")) -> breach | E15: =IF(C15>=Inputs!$C$7,Inputs!$C$5-Inputs!$C$8*B15,0) -> 77.73
A16: 0.5 | B16: =Calc!$C$42*(1-A16) -> 438 | C16: =IF(B16>0,Inputs!$C$5/B16,"n/a") -> 0.34246575 | D16: =IF(C16>=Inputs!$C$7,"breach",IF(OR(C16>=Inputs!$C$6,NOT(Calc!$C$46)),"cash sweep","ok")) -> breach | E16: =IF(C16>=Inputs!$C$7,Inputs!$C$5-Inputs!$C$8*B16,0) -> 84.3

Sheet Single-name
A1: Largest assets written down
A3: Block k writes down the k largest assets (by NAV) by the loss on Inputs; limits are recomputed on the smaller portfolio.
C15: k = 1 | D15: 1 | H15: k = 2 | I15: 2 | M15: k = 3 | N15: 3
B16: Asset | C16: Stressed NAV | D16: Capped | E16: Rank | F16: Top N | H16: Stressed NAV | I16: Capped | J16: Rank | K16: Top N | M16: Stressed NAV | N16: Capped | O16: Rank | P16: Top N
B17: =Calc!B17 -> Asset A | C17: =IF(Calc!$D17<=$D$15,Calc!$C17*(1-Inputs!$C$13),Calc!$C17) -> 0 | D17: =MIN(C17,Inputs!$C$9*C$38) -> 0 | E17: =RANK(D17,D$17:D$36,0)+COUNTIF(D$16:D16,D17) -> 11 | F17: =IF(AND(ISNUMBER(Inputs!$C$10),E17<=Inputs!$C$10),1,0) -> 0 | H17: =IF(Calc!$D17<=$I$15,Calc!$C17*(1-Inputs!$C$13),Calc!$C17) -> 0 | I17: =MIN(H17,Inputs!$C$9*H$38) -> 0 | J17: =RANK(I17,I$17:I$36,0)+COUNTIF(I$16:I16,I17) -> 10 | K17: =IF(AND(ISNUMBER(Inputs!$C$10),J17<=Inputs!$C$10),1,0) -> 0 | M17: =IF(Calc!$D17<=$N$15,Calc!$C17*(1-Inputs!$C$13),Calc!$C17) -> 0 | N17: =MIN(M17,Inputs!$C$9*M$38) -> 0 | O17: =RANK(N17,N$17:N$36,0)+COUNTIF(N$16:N16,N17) -> 9 | P17: =IF(AND(ISNUMBER(Inputs!$C$10),O17<=Inputs!$C$10),1,0) -> 0
B18: =Calc!B18 -> Asset B | C18: =IF(Calc!$D18<=$D$15,Calc!$C18*(1-Inputs!$C$13),Calc!$C18) -> 150 | D18: =MIN(C18,Inputs!$C$9*C$38) -> 150 | E18: =RANK(D18,D$17:D$36,0)+COUNTIF(D$16:D17,D18) -> 1 | F18: =IF(AND(ISNUMBER(Inputs!$C$10),E18<=Inputs!$C$10),1,0) -> 1 | H18: =IF(Calc!$D18<=$I$15,Calc!$C18*(1-Inputs!$C$13),Calc!$C18) -> 0 | I18: =MIN(H18,Inputs!$C$9*H$38) -> 0 | J18: =RANK(I18,I$17:I$36,0)+COUNTIF(I$16:I17,I18) -> 11 | K18: =IF(AND(ISNUMBER(Inputs!$C$10),J18<=Inputs!$C$10),1,0) -> 0 | M18: =IF(Calc!$D18<=$N$15,Calc!$C18*(1-Inputs!$C$13),Calc!$C18) -> 0 | N18: =MIN(M18,Inputs!$C$9*M$38) -> 0 | O18: =RANK(N18,N$17:N$36,0)+COUNTIF(N$16:N17,N18) -> 10 | P18: =IF(AND(ISNUMBER(Inputs!$C$10),O18<=Inputs!$C$10),1,0) -> 0
B19: =Calc!B19 -> Asset C | C19: =IF(Calc!$D19<=$D$15,Calc!$C19*(1-Inputs!$C$13),Calc!$C19) -> 120 | D19: =MIN(C19,Inputs!$C$9*C$38) -> 120 | E19: =RANK(D19,D$17:D$36,0)+COUNTIF(D$16:D18,D19) -> 2 | F19: =IF(AND(ISNUMBER(Inputs!$C$10),E19<=Inputs!$C$10),1,0) -> 1 | H19: =IF(Calc!$D19<=$I$15,Calc!$C19*(1-Inputs!$C$13),Calc!$C19) -> 120 | I19: =MIN(H19,Inputs!$C$9*H$38) -> 120 | J19: =RANK(I19,I$17:I$36,0)+COUNTIF(I$16:I18,I19) -> 1 | K19: =IF(AND(ISNUMBER(Inputs!$C$10),J19<=Inputs!$C$10),1,0) -> 1 | M19: =IF(Calc!$D19<=$N$15,Calc!$C19*(1-Inputs!$C$13),Calc!$C19) -> 0 | N19: =MIN(M19,Inputs!$C$9*M$38) -> 0 | O19: =RANK(N19,N$17:N$36,0)+COUNTIF(N$16:N18,N19) -> 11 | P19: =IF(AND(ISNUMBER(Inputs!$C$10),O19<=Inputs!$C$10),1,0) -> 0
B20: =Calc!B20 -> Asset D | C20: =IF(Calc!$D20<=$D$15,Calc!$C20*(1-Inputs!$C$13),Calc!$C20) -> 100 | D20: =MIN(C20,Inputs!$C$9*C$38) -> 100 | E20: =RANK(D20,D$17:D$36,0)+COUNTIF(D$16:D19,D20) -> 3 | F20: =IF(AND(ISNUMBER(Inputs!$C$10),E20<=Inputs!$C$10),1,0) -> 1 | H20: =IF(Calc!$D20<=$I$15,Calc!$C20*(1-Inputs!$C$13),Calc!$C20) -> 100 | I20: =MIN(H20,Inputs!$C$9*H$38) -> 100 | J20: =RANK(I20,I$17:I$36,0)+COUNTIF(I$16:I19,I20) -> 2 | K20: =IF(AND(ISNUMBER(Inputs!$C$10),J20<=Inputs!$C$10),1,0) -> 1 | M20: =IF(Calc!$D20<=$N$15,Calc!$C20*(1-Inputs!$C$13),Calc!$C20) -> 100 | N20: =MIN(M20,Inputs!$C$9*M$38) -> 98 | O20: =RANK(N20,N$17:N$36,0)+COUNTIF(N$16:N19,N20) -> 1 | P20: =IF(AND(ISNUMBER(Inputs!$C$10),O20<=Inputs!$C$10),1,0) -> 1
B21: =Calc!B21 -> Asset E | C21: =IF(Calc!$D21<=$D$15,Calc!$C21*(1-Inputs!$C$13),Calc!$C21) -> 90 | D21: =MIN(C21,Inputs!$C$9*C$38) -> 90 | E21: =RANK(D21,D$17:D$36,0)+COUNTIF(D$16:D20,D21) -> 4 | F21: =IF(AND(ISNUMBER(Inputs!$C$10),E21<=Inputs!$C$10),1,0) -> 1 | H21: =IF(Calc!$D21<=$I$15,Calc!$C21*(1-Inputs!$C$13),Calc!$C21) -> 90 | I21: =MIN(H21,Inputs!$C$9*H$38) -> 90 | J21: =RANK(I21,I$17:I$36,0)+COUNTIF(I$16:I20,I21) -> 3 | K21: =IF(AND(ISNUMBER(Inputs!$C$10),J21<=Inputs!$C$10),1,0) -> 1 | M21: =IF(Calc!$D21<=$N$15,Calc!$C21*(1-Inputs!$C$13),Calc!$C21) -> 90 | N21: =MIN(M21,Inputs!$C$9*M$38) -> 90 | O21: =RANK(N21,N$17:N$36,0)+COUNTIF(N$16:N20,N21) -> 2 | P21: =IF(AND(ISNUMBER(Inputs!$C$10),O21<=Inputs!$C$10),1,0) -> 1
B22: =Calc!B22 -> Asset F | C22: =IF(Calc!$D22<=$D$15,Calc!$C22*(1-Inputs!$C$13),Calc!$C22) -> 80 | D22: =MIN(C22,Inputs!$C$9*C$38) -> 80 | E22: =RANK(D22,D$17:D$36,0)+COUNTIF(D$16:D21,D22) -> 5 | F22: =IF(AND(ISNUMBER(Inputs!$C$10),E22<=Inputs!$C$10),1,0) -> 1 | H22: =IF(Calc!$D22<=$I$15,Calc!$C22*(1-Inputs!$C$13),Calc!$C22) -> 80 | I22: =MIN(H22,Inputs!$C$9*H$38) -> 80 | J22: =RANK(I22,I$17:I$36,0)+COUNTIF(I$16:I21,I22) -> 4 | K22: =IF(AND(ISNUMBER(Inputs!$C$10),J22<=Inputs!$C$10),1,0) -> 1 | M22: =IF(Calc!$D22<=$N$15,Calc!$C22*(1-Inputs!$C$13),Calc!$C22) -> 80 | N22: =MIN(M22,Inputs!$C$9*M$38) -> 80 | O22: =RANK(N22,N$17:N$36,0)+COUNTIF(N$16:N21,N22) -> 3 | P22: =IF(AND(ISNUMBER(Inputs!$C$10),O22<=Inputs!$C$10),1,0) -> 1
B23: =Calc!B23 -> Asset G | C23: =IF(Calc!$D23<=$D$15,Calc!$C23*(1-Inputs!$C$13),Calc!$C23) -> 70 | D23: =MIN(C23,Inputs!$C$9*C$38) -> 70 | E23: =RANK(D23,D$17:D$36,0)+COUNTIF(D$16:D22,D23) -> 6 | F23: =IF(AND(ISNUMBER(Inputs!$C$10),E23<=Inputs!$C$10),1,0) -> 0 | H23: =IF(Calc!$D23<=$I$15,Calc!$C23*(1-Inputs!$C$13),Calc!$C23) -> 70 | I23: =MIN(H23,Inputs!$C$9*H$38) -> 70 | J23: =RANK(I23,I$17:I$36,0)+COUNTIF(I$16:I22,I23) -> 5 | K23: =IF(AND(ISNUMBER(Inputs!$C$10),J23<=Inputs!$C$10),1,0) -> 1 | M23: =IF(Calc!$D23<=$N$15,Calc!$C23*(1-Inputs!$C$13),Calc!$C23) -> 70 | N23: =MIN(M23,Inputs!$C$9*M$38) -> 70 | O23: =RANK(N23,N$17:N$36,0)+COUNTIF(N$16:N22,N23) -> 4 | P23: =IF(AND(ISNUMBER(Inputs!$C$10),O23<=Inputs!$C$10),1,0) -> 1
B24: =Calc!B24 -> Asset H | C24: =IF(Calc!$D24<=$D$15,Calc!$C24*(1-Inputs!$C$13),Calc!$C24) -> 60 | D24: =MIN(C24,Inputs!$C$9*C$38) -> 60 | E24: =RANK(D24,D$17:D$36,0)+COUNTIF(D$16:D23,D24) -> 7 | F24: =IF(AND(ISNUMBER(Inputs!$C$10),E24<=Inputs!$C$10),1,0) -> 0 | H24: =IF(Calc!$D24<=$I$15,Calc!$C24*(1-Inputs!$C$13),Calc!$C24) -> 60 | I24: =MIN(H24,Inputs!$C$9*H$38) -> 60 | J24: =RANK(I24,I$17:I$36,0)+COUNTIF(I$16:I23,I24) -> 6 | K24: =IF(AND(ISNUMBER(Inputs!$C$10),J24<=Inputs!$C$10),1,0) -> 0 | M24: =IF(Calc!$D24<=$N$15,Calc!$C24*(1-Inputs!$C$13),Calc!$C24) -> 60 | N24: =MIN(M24,Inputs!$C$9*M$38) -> 60 | O24: =RANK(N24,N$17:N$36,0)+COUNTIF(N$16:N23,N24) -> 5 | P24: =IF(AND(ISNUMBER(Inputs!$C$10),O24<=Inputs!$C$10),1,0) -> 1
B25: =Calc!B25 -> Asset I | C25: =IF(Calc!$D25<=$D$15,Calc!$C25*(1-Inputs!$C$13),Calc!$C25) -> 40 | D25: =MIN(C25,Inputs!$C$9*C$38) -> 40 | E25: =RANK(D25,D$17:D$36,0)+COUNTIF(D$16:D24,D25) -> 8 | F25: =IF(AND(ISNUMBER(Inputs!$C$10),E25<=Inputs!$C$10),1,0) -> 0 | H25: =IF(Calc!$D25<=$I$15,Calc!$C25*(1-Inputs!$C$13),Calc!$C25) -> 40 | I25: =MIN(H25,Inputs!$C$9*H$38) -> 40 | J25: =RANK(I25,I$17:I$36,0)+COUNTIF(I$16:I24,I25) -> 7 | K25: =IF(AND(ISNUMBER(Inputs!$C$10),J25<=Inputs!$C$10),1,0) -> 0 | M25: =IF(Calc!$D25<=$N$15,Calc!$C25*(1-Inputs!$C$13),Calc!$C25) -> 40 | N25: =MIN(M25,Inputs!$C$9*M$38) -> 40 | O25: =RANK(N25,N$17:N$36,0)+COUNTIF(N$16:N24,N25) -> 6 | P25: =IF(AND(ISNUMBER(Inputs!$C$10),O25<=Inputs!$C$10),1,0) -> 0
B26: =Calc!B26 -> Asset J | C26: =IF(Calc!$D26<=$D$15,Calc!$C26*(1-Inputs!$C$13),Calc!$C26) -> 30 | D26: =MIN(C26,Inputs!$C$9*C$38) -> 30 | E26: =RANK(D26,D$17:D$36,0)+COUNTIF(D$16:D25,D26) -> 9 | F26: =IF(AND(ISNUMBER(Inputs!$C$10),E26<=Inputs!$C$10),1,0) -> 0 | H26: =IF(Calc!$D26<=$I$15,Calc!$C26*(1-Inputs!$C$13),Calc!$C26) -> 30 | I26: =MIN(H26,Inputs!$C$9*H$38) -> 30 | J26: =RANK(I26,I$17:I$36,0)+COUNTIF(I$16:I25,I26) -> 8 | K26: =IF(AND(ISNUMBER(Inputs!$C$10),J26<=Inputs!$C$10),1,0) -> 0 | M26: =IF(Calc!$D26<=$N$15,Calc!$C26*(1-Inputs!$C$13),Calc!$C26) -> 30 | N26: =MIN(M26,Inputs!$C$9*M$38) -> 30 | O26: =RANK(N26,N$17:N$36,0)+COUNTIF(N$16:N25,N26) -> 7 | P26: =IF(AND(ISNUMBER(Inputs!$C$10),O26<=Inputs!$C$10),1,0) -> 0
B27: =Calc!B27 -> Asset K | C27: =IF(Calc!$D27<=$D$15,Calc!$C27*(1-Inputs!$C$13),Calc!$C27) -> 20 | D27: =MIN(C27,Inputs!$C$9*C$38) -> 20 | E27: =RANK(D27,D$17:D$36,0)+COUNTIF(D$16:D26,D27) -> 10 | F27: =IF(AND(ISNUMBER(Inputs!$C$10),E27<=Inputs!$C$10),1,0) -> 0 | H27: =IF(Calc!$D27<=$I$15,Calc!$C27*(1-Inputs!$C$13),Calc!$C27) -> 20 | I27: =MIN(H27,Inputs!$C$9*H$38) -> 20 | J27: =RANK(I27,I$17:I$36,0)+COUNTIF(I$16:I26,I27) -> 9 | K27: =IF(AND(ISNUMBER(Inputs!$C$10),J27<=Inputs!$C$10),1,0) -> 0 | M27: =IF(Calc!$D27<=$N$15,Calc!$C27*(1-Inputs!$C$13),Calc!$C27) -> 20 | N27: =MIN(M27,Inputs!$C$9*M$38) -> 20 | O27: =RANK(N27,N$17:N$36,0)+COUNTIF(N$16:N26,N27) -> 8 | P27: =IF(AND(ISNUMBER(Inputs!$C$10),O27<=Inputs!$C$10),1,0) -> 0
B28: =Calc!B28 | C28: =IF(Calc!$D28<=$D$15,Calc!$C28*(1-Inputs!$C$13),Calc!$C28) -> 0 | D28: =MIN(C28,Inputs!$C$9*C$38) -> 0 | E28: =RANK(D28,D$17:D$36,0)+COUNTIF(D$16:D27,D28) -> 12 | F28: =IF(AND(ISNUMBER(Inputs!$C$10),E28<=Inputs!$C$10),1,0) -> 0 | H28: =IF(Calc!$D28<=$I$15,Calc!$C28*(1-Inputs!$C$13),Calc!$C28) -> 0 | I28: =MIN(H28,Inputs!$C$9*H$38) -> 0 | J28: =RANK(I28,I$17:I$36,0)+COUNTIF(I$16:I27,I28) -> 12 | K28: =IF(AND(ISNUMBER(Inputs!$C$10),J28<=Inputs!$C$10),1,0) -> 0 | M28: =IF(Calc!$D28<=$N$15,Calc!$C28*(1-Inputs!$C$13),Calc!$C28) -> 0 | N28: =MIN(M28,Inputs!$C$9*M$38) -> 0 | O28: =RANK(N28,N$17:N$36,0)+COUNTIF(N$16:N27,N28) -> 12 | P28: =IF(AND(ISNUMBER(Inputs!$C$10),O28<=Inputs!$C$10),1,0) -> 0
... B36: =Calc!B36 | C36: =IF(Calc!$D36<=$D$15,Calc!$C36*(1-Inputs!$C$13),Calc!$C36) -> 0 | D36: =MIN(C36,Inputs!$C$9*C$38) -> 0 | E36: =RANK(D36,D$17:D$36,0)+COUNTIF(D$16:D35,D36) -> 20 | F36: =IF(AND(ISNUMBER(Inputs!$C$10),E36<=Inputs!$C$10),1,0) -> 0 | H36: =IF(Calc!$D36<=$I$15,Calc!$C36*(1-Inputs!$C$13),Calc!$C36) -> 0 | I36: =MIN(H36,Inputs!$C$9*H$38) -> 0 | J36: =RANK(I36,I$17:I$36,0)+COUNTIF(I$16:I35,I36) -> 20 | K36: =IF(AND(ISNUMBER(Inputs!$C$10),J36<=Inputs!$C$10),1,0) -> 0 | M36: =IF(Calc!$D36<=$N$15,Calc!$C36*(1-Inputs!$C$13),Calc!$C36) -> 0 | N36: =MIN(M36,Inputs!$C$9*M$38) -> 0 | O36: =RANK(N36,N$17:N$36,0)+COUNTIF(N$16:N35,N36) -> 20 | P36: =IF(AND(ISNUMBER(Inputs!$C$10),O36<=Inputs!$C$10),1,0) -> 0
B38: Total NAV | C38: =SUM(C17:C36) -> 760 | H38: =SUM(H17:H36) -> 610 | M38: =SUM(M17:M36) -> 490
B39: Eligible after single-asset cap | C39: =SUM(D17:D36) -> 760 | H39: =SUM(I17:I36) -> 610 | M39: =SUM(N17:N36) -> 488
B40: Top-N capped total | C40: =SUMPRODUCT(D17:D36,F17:F36) -> 540 | H40: =SUMPRODUCT(I17:I36,K17:K36) -> 460 | M40: =SUMPRODUCT(N17:N36,P17:P36) -> 398
B41: Excluded by top-N limit | C41: =IF(AND(ISNUMBER(Inputs!$C$10),ISNUMBER(Inputs!$C$11)),MAX(0,C40-Inputs!$C$11*C39),0) -> 84 | H41: =IF(AND(ISNUMBER(Inputs!$C$10),ISNUMBER(Inputs!$C$11)),MAX(0,H40-Inputs!$C$11*H39),0) -> 94 | M41: =IF(AND(ISNUMBER(Inputs!$C$10),ISNUMBER(Inputs!$C$11)),MAX(0,M40-Inputs!$C$11*M39),0) -> 105.2
B42: Eligible NAV | C42: =C39-C41 -> 676 | H42: =H39-H41 -> 516 | M42: =M39-M41 -> 382.8
B43: LTV | C43: =IF(C42>0,Inputs!$C$5/C42,"n/a") -> 0.22189349 | H43: =IF(H42>0,Inputs!$C$5/H42,"n/a") -> 0.29069767 | M43: =IF(M42>0,Inputs!$C$5/M42,"n/a") -> 0.39184953
B44: Assets with value | C44: =COUNTIF(C17:C36,">0") -> 10 | H44: =COUNTIF(H17:H36,">0") -> 9 | M44: =COUNTIF(M17:M36,">0") -> 8
B45: Diversity covenant met | C45: =IF(ISNUMBER(Inputs!$C$12),C44>=Inputs!$C$12,TRUE()) -> TRUE | H45: =IF(ISNUMBER(Inputs!$C$12),H44>=Inputs!$C$12,TRUE()) -> FALSE | M45: =IF(ISNUMBER(Inputs!$C$12),M44>=Inputs!$C$12,TRUE()) -> FALSE
B46: Status | C46: =IF(C43>=Inputs!$C$7,"breach",IF(OR(C43>=Inputs!$C$6,NOT(C45)),"cash sweep","ok")) -> cash sweep | H46: =IF(H43>=Inputs!$C$7,"breach",IF(OR(H43>=Inputs!$C$6,NOT(H45)),"cash sweep","ok")) -> breach | M46: =IF(M43>=Inputs!$C$7,"breach",IF(OR(M43>=Inputs!$C$6,NOT(M45)),"cash sweep","ok")) -> breach
B47: Further uniform drawdown to breach | C47: =MAX(0,1-Inputs!$C$5/(Inputs!$C$7*C42)) -> 0.11242604 | H47: =MAX(0,1-Inputs!$C$5/(Inputs!$C$7*H42)) -> 0 | M47: =MAX(0,1-Inputs!$C$5/(Inputs!$C$7*M42)) -> 0

Sheet Checks
A1: Checks
A3: Internal consistency (must all be TRUE)
A5: Cure target <= sweep level <= breach level < 100% | B5: =AND(Inputs!C8<=Inputs!C6,Inputs!C6<=Inputs!C7,Inputs!C7<1) -> TRUE
A6: No negative NAVs | B6: =COUNTIF(Inputs!C17:C36,"<0")=0 -> TRUE
A7: Eligible NAV <= total NAV | B7: =Calc!C42<=Calc!C38 -> TRUE
A8: Capped ranks are 1..20 with no ties | B8: =AND(SUM(Calc!F17:F36)=210,MIN(Calc!F17:F36)=1,MAX(Calc!F17:F36)=20) -> TRUE
A9: LTV at the breakeven drawdown equals the breach level | B9: =ABS(Inputs!C5/(Calc!C42*(1-Calc!C49))-Inputs!C7)<0.000000001 -> TRUE
A10: Top-N exclusion is not negative | B10: =Calc!C41>=0 -> TRUE
A12: Overall | B12: =IF(AND(B5:B10),"ALL CHECKS PASS","CHECK FAILED") -> ALL CHECKS PASS
A15: Cross-check against the Python model (shipped inputs only)
A16: Reference values from: fund-finance-lab nav --config examples/nav_facility_covenants_hypothetical.json. They are expected to differ once inputs change.
A18: Metric | B18: Python | C18: Workbook | D18: Match
A19: Eligible NAV | B19: 876 | C19: =Calc!C42 -> 876 | D19: =IF(ABS(C19-B19)<0.000001,"match","MISMATCH") -> match
A20: LTV | B20: 0.17123288 | C20: =Calc!C44 -> 0.17123288 | D20: =IF(ABS(C20-B20)<0.000001,"match","MISMATCH") -> match
A21: Uniform drawdown to sweep | B21: 0.14383562 | C21: =Calc!C48 -> 0.14383562 | D21: =IF(ABS(C21-B21)<0.000001,"match","MISMATCH") -> match
A22: Uniform drawdown to breach | B22: 0.31506849 | C22: =Calc!C49 -> 0.31506849 | D22: =IF(ABS(C22-B22)<0.000001,"match","MISMATCH") -> match
A23: Eligible NAV, largest asset written off | B23: 676 | C23: ='Single-name'!C42 -> 676 | D23: =IF(ABS(C23-B23)<0.000001,"match","MISMATCH") -> match
A24: Eligible NAV, two largest written off | B24: 516 | C24: ='Single-name'!H42 -> 516 | D24: =IF(ABS(C24-B24)<0.000001,"match","MISMATCH") -> match
A25: Eligible NAV, three largest written off | B25: 382.8 | C25: ='Single-name'!M42 -> 382.8 | D25: =IF(ABS(C25-B25)<0.000001,"match","MISMATCH") -> match
A26: Status at base | B26: ok | C26: =Calc!C47 -> ok | D26: =IF(C26=B26,"match","MISMATCH") -> match
